aiterio/__init__.py
aiterio/component.py
aiterio/py.typed
aiterio-0.1.6.dist-info/METADATA
aiterio-0.1.6.dist-info/WHEEL
aiterio-0.1.6.dist-info/licenses/LICENSE
aiterio-0.1.6.dist-info/RECORD
