Metadata-Version: 2.3
Name: aiterio
Version: 0.1.6
Summary: AsyncIterator based connectable components
Author-email: DorskFR <dorsk.dev@gmail.com>
License: MIT
License-File: LICENSE
Requires-Python: >=3.10
